transformations_2d/__init__.py
transformations_2d/geometry.py
transformations_2d-0.2.0.dist-info/licenses/LICENSE
transformations_2d-0.2.0.dist-info/METADATA
transformations_2d-0.2.0.dist-info/WHEEL
transformations_2d-0.2.0.dist-info/top_level.txt
transformations_2d-0.2.0.dist-info/RECORD
