Metadata-Version: 2.4
Name: transformations_2d
Version: 0.2.0
Summary: A lightweight and intuitive Python package for applying 2D geometric transformations—such as translation, scaling, rotation, shearing, and reflection—to points and polygons. Ideal for graphics, simulations, and educational use.
Author-email: Mainak Debnath <mainak7debnath@gmail.com>
License: MIT
Project-URL: Homepage, https://github.com/mainak-debnath/transformations_2d
Project-URL: Bug Tracker, https://github.com/mainak-debnath/transformations_2d/issues
Keywords: 2d,geometry,transformations,translation,scaling,rotation,shearing,reflection
Classifier: Programming Language :: Python :: 3
Classifier: License :: OSI Approved :: MIT License
Classifier: Operating System :: OS Independent
Requires-Python: >=3.8
License-File: LICENSE
Dynamic: license-file
